moorlib/__init__.py
moorlib/core/__init__.py
moorlib/core/feedback/__init__.py
moorlib/core/feedback/data.py
moorlib/core/feedback/decorators.py
moorlib/core/feedback/errors.py
moorlib/core/feedback/feedback.py
moorlib-0.1.0.dist-info/licenses/LICENSE
moorlib-0.1.0.dist-info/METADATA
moorlib-0.1.0.dist-info/WHEEL
moorlib-0.1.0.dist-info/top_level.txt
moorlib-0.1.0.dist-info/RECORD
