Metadata-Version: 2.4
Name: moorlib
Version: 0.1.0
Summary: moorlib: TODO
Author-email: Amirhossein Pashaeehir <ahph1380@gmail.com>
Requires-Python: >=3.12
License-File: LICENSE
Requires-Dist: iniconfig>=2.0.0
Requires-Dist: mypy>=1.15.0
Requires-Dist: mypy-extensions>=1.0.0
Requires-Dist: packaging>=24.2
Requires-Dist: pluggy>=1.5.0
Requires-Dist: pytest>=8.3.4
Requires-Dist: typing_extensions>=4.12.2
Requires-Dist: ruff>=0.9.10
Dynamic: license-file
